{"img_id": "scene_006_1.jpg", "human_num": 29, "boxes": [], "points": [{"x": 8.75, "y": 66.25}, {"x": 7.5, "y": 77.25}, {"x": 70.25, "y": 101.5}, {"x": 67.0, "y": 140.25}, {"x": 123.5, "y": 144.25}, {"x": 129.5, "y": 164.0}, {"x": 151.25, "y": 114.0}, {"x": 142.0, "y": 131.0}, {"x": 193.25, "y": 127.75}, {"x": 22.0, "y": 316.5}, {"x": 43.75, "y": 179.5}, {"x": 59.0, "y": 206.0}, {"x": 227.0, "y": 145.75}, {"x": 207.75, "y": 158.0}, {"x": 306.0, "y": 148.75}, {"x": 405.5, "y": 220.0}, {"x": 396.75, "y": 192.75}, {"x": 410.25, "y": 178.75}, {"x": 411.25, "y": 169.5}, {"x": 409.5, "y": 156.5}, {"x": 418.5, "y": 152.25}, {"x": 387.5, "y": 127.0}, {"x": 390.0, "y": 140.5}, {"x": 391.75, "y": 148.75}, {"x": 366.25, "y": 127.0}, {"x": 332.75, "y": 123.0}, {"x": 334.25, "y": 139.25}, {"x": 461.0, "y": 151.5}, {"x": 459.75, "y": 193.0}]}